[
  {
    "name": "fioreses",
    "ip": "10.90.90.90",
    "get_community": "public",
    "set_community": "private",
    "initial_port": "1",
    "dont_block": [
      "5",
      "1"
    ],
    "port_quantity": "24"
  },
  {
    "name": "leo",
    "ip": "192.168.0.1",
    "get_community": "servidorgamer",
    "set_community": "servidorgamer",
    "initial_port": "49153",
    "dont_block": [
      "1",
      "2",
      "4",
      "21",
      "22",
      "24"
    ],
    "port_quantity": "24"
  },
  {
    "name": "virtual",
    "ip": "127.0.0.1",
    "port": "16100",
    "get_community": "cisco_16_switch",
    "set_community": "cisco_16_switch",
    "initial_port": "11001",
    "dont_block": [
      "1"
    ],
    "port_quantity": "4"
  }
]